Self_Quarantine/__init__.py
Self_Quarantine-0.0.1.dist-info/LICENSE
Self_Quarantine-0.0.1.dist-info/METADATA
Self_Quarantine-0.0.1.dist-info/WHEEL
Self_Quarantine-0.0.1.dist-info/top_level.txt
Self_Quarantine-0.0.1.dist-info/RECORD
