Metadata-Version: 2.1
Name: Self-Quarantine
Version: 0.0.1
Summary: self tracking application
Home-page: https://github.com/abhinavclemson/Self_Quarantine
Author: Abhinav Singh
Author-email: abhinav.coder@gmail.com
License: UNKNOWN
Platform: UNKNOWN
Classifier: Programming Language :: Python :: 3
Classifier: License :: OSI Approved :: MIT License
Classifier: Operating System :: OS Independent
Requires-Python: >=3.6
